odoo8_addon_l10n_fr_business_document_import-8.0.1.0.0.99.dev3-py2.7-nspkg.pth
odoo8_addon_l10n_fr_business_document_import-8.0.1.0.0.99.dev3.dist-info/METADATA
odoo8_addon_l10n_fr_business_document_import-8.0.1.0.0.99.dev3.dist-info/RECORD
odoo8_addon_l10n_fr_business_document_import-8.0.1.0.0.99.dev3.dist-info/WHEEL
odoo8_addon_l10n_fr_business_document_import-8.0.1.0.0.99.dev3.dist-info/namespace_packages.txt
odoo8_addon_l10n_fr_business_document_import-8.0.1.0.0.99.dev3.dist-info/top_level.txt
odoo_addons/l10n_fr_business_document_import/README.rst
odoo_addons/l10n_fr_business_document_import/__init__.py
odoo_addons/l10n_fr_business_document_import/__openerp__.py
odoo_addons/l10n_fr_business_document_import/i18n/l10n_fr_business_document_import.pot
odoo_addons/l10n_fr_business_document_import/models/__init__.py
odoo_addons/l10n_fr_business_document_import/models/business_document_import.py
odoo_addons/l10n_fr_business_document_import/static/description/icon.png
