Metadata-Version: 2.1
Name: odoo8-addon-l10n-fr-business-document-import
Version: 8.0.1.0.0.99.dev3
Summary: Adapt the module base_business_document_import for France
Home-page: http://www.akretion.com
Author: Akretion,Odoo Community Association (OCA)
Author-email: support@odoo-community.org
License: AGPL-3
Platform: UNKNOWN
Classifier: Programming Language :: Python
Classifier: Framework :: Odoo
Classifier: License :: OSI Approved :: GNU Affero General Public License v3
Requires-Python: ~=2.7
Requires-Dist: odoo8-addon-base-business-document-import
Requires-Dist: odoo8-addon-l10n-fr-siret
Requires-Dist: odoo (<9.0a,>=8.0a)
